{
    "classes": [
        {
            "className": "WhisperModelManager",
            "lineNumber": 21,
            "methods": [
                {
                    "access": "public",
                    "arguments": [
                        {
                            "name": "modelId",
                            "type": "QString"
                        }
                    ],
                    "index": 12,
                    "isConst": true,
                    "lineNumber": 68,
                    "name": "isModelAvailable",
                    "returnType": "bool"
                },
                {
                    "access": "public",
                    "arguments": [
                        {
                            "name": "modelId",
                            "type": "QString"
                        }
                    ],
                    "index": 13,
                    "lineNumber": 71,
                    "name": "downloadModel",
                    "returnType": "void"
                },
                {
                    "access": "public",
                    "index": 14,
                    "lineNumber": 74,
                    "name": "cancelDownload",
                    "returnType": "void"
                },
                {
                    "access": "public",
                    "arguments": [
                        {
                            "name": "modelId",
                            "type": "QString"
                        }
                    ],
                    "index": 15,
                    "lineNumber": 79,
                    "name": "deleteModel",
                    "returnType": "void"
                },
                {
                    "access": "public",
                    "arguments": [
                        {
                            "name": "modelId",
                            "type": "QString"
                        }
                    ],
                    "index": 16,
                    "lineNumber": 82,
                    "name": "setActiveModel",
                    "returnType": "void"
                },
                {
                    "access": "public",
                    "index": 17,
                    "isConst": true,
                    "lineNumber": 85,
                    "name": "totalDiskUsage",
                    "returnType": "qint64"
                },
                {
                    "access": "public",
                    "arguments": [
                        {
                            "name": "count",
                            "type": "int"
                        }
                    ],
                    "index": 18,
                    "lineNumber": 94,
                    "name": "setThreadCount",
                    "returnType": "void"
                },
                {
                    "access": "public",
                    "arguments": [
                        {
                            "name": "enabled",
                            "type": "bool"
                        }
                    ],
                    "index": 19,
                    "lineNumber": 98,
                    "name": "setAutoDetectLanguage",
                    "returnType": "void"
                },
                {
                    "access": "public",
                    "arguments": [
                        {
                            "name": "lang",
                            "type": "QString"
                        }
                    ],
                    "index": 20,
                    "lineNumber": 102,
                    "name": "setSelectedLanguage",
                    "returnType": "void"
                },
                {
                    "access": "public",
                    "arguments": [
                        {
                            "name": "mode",
                            "type": "QString"
                        }
                    ],
                    "index": 21,
                    "lineNumber": 106,
                    "name": "setGlobalMode",
                    "returnType": "void"
                },
                {
                    "access": "public",
                    "arguments": [
                        {
                            "name": "modelId",
                            "type": "QString"
                        }
                    ],
                    "index": 22,
                    "lineNumber": 110,
                    "name": "benchmarkModel",
                    "returnType": "void"
                },
                {
                    "access": "public",
                    "index": 23,
                    "isConst": true,
                    "lineNumber": 114,
                    "name": "deviceCanHandleLocal",
                    "returnType": "bool"
                },
                {
                    "access": "public",
                    "index": 24,
                    "isConst": true,
                    "lineNumber": 117,
                    "name": "recommendedMode",
                    "returnType": "QString"
                }
            ],
            "object": true,
            "properties": [
                {
                    "constant": false,
                    "designable": true,
                    "final": false,
                    "index": 0,
                    "lineNumber": 24,
                    "name": "availableModels",
                    "notify": "availableModelsChanged",
                    "read": "availableModels",
                    "required": false,
                    "scriptable": true,
                    "stored": true,
                    "type": "QVariantList",
                    "user": false
                },
                {
                    "constant": false,
                    "designable": true,
                    "final": false,
                    "index": 1,
                    "lineNumber": 25,
                    "name": "activeModelId",
                    "notify": "activeModelChanged",
                    "read": "activeModelId",
                    "required": false,
                    "scriptable": true,
                    "stored": true,
                    "type": "QString",
                    "user": false,
                    "write": "setActiveModel"
                },
                {
                    "constant": false,
                    "designable": true,
                    "final": false,
                    "index": 2,
                    "lineNumber": 26,
                    "name": "isDownloading",
                    "notify": "isDownloadingChanged",
                    "read": "isDownloading",
                    "required": false,
                    "scriptable": true,
                    "stored": true,
                    "type": "bool",
                    "user": false
                },
                {
                    "constant": false,
                    "designable": true,
                    "final": false,
                    "index": 3,
                    "lineNumber": 27,
                    "name": "downloadProgress",
                    "notify": "downloadProgressChanged",
                    "read": "downloadProgress",
                    "required": false,
                    "scriptable": true,
                    "stored": true,
                    "type": "double",
                    "user": false
                },
                {
                    "constant": false,
                    "designable": true,
                    "final": false,
                    "index": 4,
                    "lineNumber": 28,
                    "name": "downloadError",
                    "notify": "downloadErrorChanged",
                    "read": "downloadError",
                    "required": false,
                    "scriptable": true,
                    "stored": true,
                    "type": "QString",
                    "user": false
                },
                {
                    "constant": true,
                    "designable": true,
                    "final": false,
                    "index": 5,
                    "lineNumber": 29,
                    "name": "gpuAccelerated",
                    "read": "gpuAccelerated",
                    "required": false,
                    "scriptable": true,
                    "stored": true,
                    "type": "bool",
                    "user": false
                },
                {
                    "constant": true,
                    "designable": true,
                    "final": false,
                    "index": 6,
                    "lineNumber": 30,
                    "name": "gpuBackend",
                    "read": "gpuBackend",
                    "required": false,
                    "scriptable": true,
                    "stored": true,
                    "type": "QString",
                    "user": false
                },
                {
                    "constant": false,
                    "designable": true,
                    "final": false,
                    "index": 7,
                    "lineNumber": 31,
                    "name": "threadCount",
                    "notify": "threadCountChanged",
                    "read": "threadCount",
                    "required": false,
                    "scriptable": true,
                    "stored": true,
                    "type": "int",
                    "user": false,
                    "write": "setThreadCount"
                },
                {
                    "constant": false,
                    "designable": true,
                    "final": false,
                    "index": 8,
                    "lineNumber": 32,
                    "name": "autoDetectLanguage",
                    "notify": "autoDetectLanguageChanged",
                    "read": "autoDetectLanguage",
                    "required": false,
                    "scriptable": true,
                    "stored": true,
                    "type": "bool",
                    "user": false,
                    "write": "setAutoDetectLanguage"
                },
                {
                    "constant": true,
                    "designable": true,
                    "final": false,
                    "index": 9,
                    "lineNumber": 33,
                    "name": "onnxAvailable",
                    "read": "onnxAvailable",
                    "required": false,
                    "scriptable": true,
                    "stored": true,
                    "type": "bool",
                    "user": false
                },
                {
                    "constant": false,
                    "designable": true,
                    "final": false,
                    "index": 10,
                    "lineNumber": 34,
                    "name": "globalMode",
                    "notify": "globalModeChanged",
                    "read": "globalMode",
                    "required": false,
                    "scriptable": true,
                    "stored": true,
                    "type": "QString",
                    "user": false,
                    "write": "setGlobalMode"
                },
                {
                    "constant": false,
                    "designable": true,
                    "final": false,
                    "index": 11,
                    "lineNumber": 35,
                    "name": "selectedLanguage",
                    "notify": "selectedLanguageChanged",
                    "read": "selectedLanguage",
                    "required": false,
                    "scriptable": true,
                    "stored": true,
                    "type": "QString",
                    "user": false,
                    "write": "setSelectedLanguage"
                }
            ],
            "qualifiedClassName": "WhisperModelManager",
            "signals": [
                {
                    "access": "public",
                    "index": 0,
                    "lineNumber": 120,
                    "name": "availableModelsChanged",
                    "returnType": "void"
                },
                {
                    "access": "public",
                    "index": 1,
                    "lineNumber": 121,
                    "name": "activeModelChanged",
                    "returnType": "void"
                },
                {
                    "access": "public",
                    "index": 2,
                    "lineNumber": 122,
                    "name": "isDownloadingChanged",
                    "returnType": "void"
                },
                {
                    "access": "public",
                    "index": 3,
                    "lineNumber": 123,
                    "name": "downloadProgressChanged",
                    "returnType": "void"
                },
                {
                    "access": "public",
                    "index": 4,
                    "lineNumber": 124,
                    "name": "downloadErrorChanged",
                    "returnType": "void"
                },
                {
                    "access": "public",
                    "arguments": [
                        {
                            "name": "modelId",
                            "type": "QString"
                        }
                    ],
                    "index": 5,
                    "lineNumber": 125,
                    "name": "modelReady",
                    "returnType": "void"
                },
                {
                    "access": "public",
                    "arguments": [
                        {
                            "name": "modelId",
                            "type": "QString"
                        }
                    ],
                    "index": 6,
                    "lineNumber": 126,
                    "name": "modelDeleted",
                    "returnType": "void"
                },
                {
                    "access": "public",
                    "index": 7,
                    "lineNumber": 127,
                    "name": "threadCountChanged",
                    "returnType": "void"
                },
                {
                    "access": "public",
                    "index": 8,
                    "lineNumber": 128,
                    "name": "autoDetectLanguageChanged",
                    "returnType": "void"
                },
                {
                    "access": "public",
                    "index": 9,
                    "lineNumber": 129,
                    "name": "selectedLanguageChanged",
                    "returnType": "void"
                },
                {
                    "access": "public",
                    "index": 10,
                    "lineNumber": 130,
                    "name": "globalModeChanged",
                    "returnType": "void"
                },
                {
                    "access": "public",
                    "arguments": [
                        {
                            "name": "modelId",
                            "type": "QString"
                        },
                        {
                            "name": "msPerChunk",
                            "type": "int"
                        }
                    ],
                    "index": 11,
                    "lineNumber": 131,
                    "name": "benchmarkResult",
                    "returnType": "void"
                }
            ],
            "superClasses": [
                {
                    "access": "public",
                    "name": "QObject"
                }
            ]
        }
    ],
    "inputFile": "WhisperModelManager.h",
    "outputRevision": 69
}
